rule34/__init__.py
rule34/objectClasses.py
rule34/rule34.py
rule34/test.py
rule34_new-1.0.4.dist-info/METADATA
rule34_new-1.0.4.dist-info/WHEEL
rule34_new-1.0.4.dist-info/top_level.txt
rule34_new-1.0.4.dist-info/RECORD
